setup.cfg
setup.py
solarshed/__init__.py
solarshed/server.py
solarshed.egg-info/PKG-INFO
solarshed.egg-info/SOURCES.txt
solarshed.egg-info/dependency_links.txt
solarshed.egg-info/not-zip-safe
solarshed.egg-info/requires.txt
solarshed.egg-info/top_level.txt
solarshed/controllers/__init__.py
solarshed/controllers/renogy_rover.py